tango_data_structures/__init__.py
tango_data_structures/utils.py
tango_data_structures-1.0.0.dist-info/METADATA
tango_data_structures-1.0.0.dist-info/WHEEL
tango_data_structures-1.0.0.dist-info/licenses/LICENSE
tango_data_structures-1.0.0.dist-info/RECORD
